AUTHORS
Changelog
LICENSE
MANIFEST.in
README
README.rst
TODO
setup.py
celerymon/__init__.py
celerymon/consumer.py
celerymon/service.py
celerymon/web.py
celerymon.egg-info/PKG-INFO
celerymon.egg-info/SOURCES.txt
celerymon.egg-info/dependency_links.txt
celerymon.egg-info/entry_points.txt
celerymon.egg-info/not-zip-safe
celerymon.egg-info/requires.txt
celerymon.egg-info/top_level.txt
celerymon/bin/__init__.py
celerymon/bin/celerymon.py
celerymon/handlers/__init__.py
celerymon/handlers/api.py
celerymon/handlers/main.py
celerymon/management/__init__.py
celerymon/management/commands/__init__.py
celerymon/management/commands/celerymon.py
celerymon/static/analytics.tsv
celerymon/static/favicon.ico
celerymon/static/css/master.css
celerymon/static/highcharts/index.htm
celerymon/static/highcharts/examples/analytics.tsv
celerymon/static/highcharts/examples/area-basic.htm
celerymon/static/highcharts/examples/area-inverted.htm
celerymon/static/highcharts/examples/area-missing.htm
celerymon/static/highcharts/examples/area-negative.htm
celerymon/static/highcharts/examples/area-stacked-percent.htm
celerymon/static/highcharts/examples/area-stacked.htm
celerymon/static/highcharts/examples/areaspline.htm
celerymon/static/highcharts/examples/bar-basic.htm
celerymon/static/highcharts/examples/bar-negative-stack.htm
celerymon/static/highcharts/examples/bar-stacked.htm
celerymon/static/highcharts/examples/column-basic.htm
celerymon/static/highcharts/examples/column-drilldown.htm
celerymon/static/highcharts/examples/column-negative.htm
celerymon/static/highcharts/examples/column-parsed.htm
celerymon/static/highcharts/examples/column-rotated-labels.htm
celerymon/static/highcharts/examples/column-stacked-and-grouped.htm
celerymon/static/highcharts/examples/column-stacked-percent.htm
celerymon/static/highcharts/examples/column-stacked.htm
celerymon/static/highcharts/examples/combo-dual-axes.htm
celerymon/static/highcharts/examples/combo-multi-axes.htm
celerymon/static/highcharts/examples/combo-regression.htm
celerymon/static/highcharts/examples/combo.htm
celerymon/static/highcharts/examples/dynamic-click-to-add.htm
celerymon/static/highcharts/examples/dynamic-master-detail.htm
