Metadata-Version: 1.0
Name: celerymon
Version: 1.0.3
Summary: Real-time monitoring of Celery workers.
Home-page: http://github.com/celery/celerymon/
Author: Ask Solem
Author-email: ask@celeryproject.org
License: BSD
Platform: any
Classifier: Development Status :: 5 - Production/Stable
Classifier: Operating System :: OS Independent
Classifier: Programming Language :: Python
Classifier: Programming Language :: Python :: 2.5
Classifier: Programming Language :: Python :: 2.6
Classifier: Programming Language :: Python :: 2.7
Classifier: License :: OSI Approved :: BSD License
Classifier: Operating System :: POSIX
Classifier: Topic :: System :: Monitoring
Classifier: Topic :: System :: Distributed Computing
